{
  "type": "minecraft:crafting_shapeless",
  "ingredients": [
    {
      "item": "minecraft:apple"
    },
    {
      "item": "minecraft:apple"
    },
    {
      "item": "minecraft:apple"
    },
    {
      "item": "minecraft:apple"
    },
    {
      "item": "minecraft:apple"
    },
    {
      "item": "minecraft:apple"
    },
    {
      "item": "minecraft:apple"
    },
    {
      "item": "minecraft:apple"
    },
    {
      "item": "minecraft:apple"
    }
  ],
  "result": {
    "item": "block_of:apple_block",
    "count": 1
  }
}